[{"id":"m3u-1771698261475-5844","name":"De Volta ao Mar (2024)","url":"http://site.poupadefrutas.shop:80/movie/cleberson24/24danbury888BBB/1152750.mp4","active":true,"category":"Drama e História","type":"movie","isAdult":false,"logo":"https://image.tmdb.org/t/p/w600_and_h900_bestv2/a1PVrIfWecgmzv5x799NVMssUAp.jpg","tmdb":null},{"id":"m3u-1771698261475-7942","name":"Encontro com o Ditador (2024)","url":"http://site.poupadefrutas.shop:80/movie/cleberson24/24danbury888BBB/1152757.mp4","active":true,"category":"Drama e História","type":"movie","isAdult":false,"logo":"https://image.tmdb.org/t/p/w600_and_h900_bestv2/4x52sBptAvaowVGQ23OuNWtz5Ze.jpg","tmdb":null},{"id":"m3u-1771698261475-1092","name":"Histórias Invisíveis (2024)","url":"http://site.poupadefrutas.shop:80/movie/cleberson24/24danbury888BBB/1152784.mp4","active":true,"category":"Drama e História","type":"movie","isAdult":false,"logo":"https://image.tmdb.org/t/p/w600_and_h900_bestv2/v4YIoskn5M1ZZbDn9kaFPtmJO4Z.jpg","tmdb":null},{"id":"m3u-1771698261476-2556","name":"A Luta (2021)","url":"http://site.poupadefrutas.shop:80/movie/cleberson24/24danbury888BBB/1153012.mp4","active":true,"category":"Drama e História","type":"movie","isAdult":false,"logo":"https://image.tmdb.org/t/p/w600_and_h900_bestv2/u7hSjwNjMYtORwOErHNLpAXeIEp.jpg","tmdb":null},{"id":"m3u-1771698261476-5065","name":"Inocencia (2020)","url":"http://site.poupadefrutas.shop:80/movie/cleberson24/24danbury888BBB/1153014.mp4","active":true,"category":"Drama e História","type":"movie","isAdult":false,"logo":"https://image.tmdb.org/t/p/w600_and_h900_bestv2/j0HjgoBSMQx1Mmd9fVRwQ4bwBci.jpg","tmdb":null},{"id":"m3u-1771698261476-1160","name":"Fuga de Natal (2018)","url":"http://site.poupadefrutas.shop:80/movie/cleberson24/24danbury888BBB/1153037.mp4","active":true,"category":"Drama e História","type":"movie","isAdult":false,"logo":"https://image.tmdb.org/t/p/w600_and_h900_bestv2/fG1rA08uGLTdvY0VBTsDllfdP9z.jpg","tmdb":null},{"id":"m3u-1771698261477-8305","name":"Agreste (2024)","url":"http://site.poupadefrutas.shop:80/movie/cleberson24/24danbury888BBB/1153164.mp4","active":true,"category":"Drama e História","type":"movie","isAdult":false,"logo":"https://image.tmdb.org/t/p/w600_and_h900_bestv2/nG6GFSM8KdKqqMbU3JgaTfzVds0.jpg","tmdb":null},{"id":"m3u-1771698261477-549","name":"Aqui (2024)","url":"http://site.poupadefrutas.shop:80/movie/cleberson24/24danbury888BBB/1153175.mp4","active":true,"category":"Drama e História","type":"movie","isAdult":false,"logo":"https://image.tmdb.org/t/p/w600_and_h900_bestv2/rmqBc3qRXeSgzCcWY2H4l9M8eIT.jpg","tmdb":null},{"id":"m3u-1771698261477-8495","name":"A Contadora de Filmes (2023)","url":"http://site.poupadefrutas.shop:80/movie/cleberson24/24danbury888BBB/1153182.mp4","active":true,"category":"Drama e História","type":"movie","isAdult":false,"logo":"https://image.tmdb.org/t/p/w600_and_h900_bestv2/tzCEvNVmVZVoCtVD2HnEQw6IEGn.jpg","tmdb":null},{"id":"m3u-1771698261477-5107","name":"Reagan (2024)","url":"http://site.poupadefrutas.shop:80/movie/cleberson24/24danbury888BBB/1153185.mp4","active":true,"category":"Drama e História","type":"movie","isAdult":false,"logo":"https://image.tmdb.org/t/p/w600_and_h900_bestv2/o21NB4f5fNk1dtrRlyAmA0C0cb3.jpg","tmdb":null},{"id":"m3u-1771698261477-1107","name":"Anuja (2024)","url":"http://site.poupadefrutas.shop:80/movie/cleberson24/24danbury888BBB/1153213.mp4","active":true,"category":"Drama e História","type":"movie","isAdult":false,"logo":"https://image.tmdb.org/t/p/w600_and_h900_bestv2/84YVJuVaJ0tlo244eRUTNdIe9uL.jpg","tmdb":null},{"id":"m3u-1771698261477-6948","name":"Consentimento (2022)","url":"http://site.poupadefrutas.shop:80/movie/cleberson24/24danbury888BBB/1153214.mp4","active":true,"category":"Drama e História","type":"movie","isAdult":false,"logo":"https://image.tmdb.org/t/p/w600_and_h900_bestv2/kb5L9DbZTGeRnsrBrVD5MXlWNWG.jpg","tmdb":null},{"id":"m3u-1771698261477-9387","name":"Inexplicável (2024)","url":"http://site.poupadefrutas.shop:80/movie/cleberson24/24danbury888BBB/1153218.mp4","active":true,"category":"Drama e História","type":"movie","isAdult":false,"logo":"https://image.tmdb.org/t/p/w600_and_h900_bestv2/yiWrMyJA6yYo147S9Xu7Cy4ghEI.jpg","tmdb":null},{"id":"m3u-1771698261477-2121","name":"Gölgeler ve Suretler (2010)","url":"http://site.poupadefrutas.shop:80/movie/cleberson24/24danbury888BBB/1153247.mp4","active":true,"category":"Drama e História","type":"movie","isAdult":false,"logo":"https://image.tmdb.org/t/p/w600_and_h900_bestv2/2VIkKj6XY7pZ45HnslVuc3IvAV.jpg","tmdb":null},{"id":"m3u-1771698261477-881","name":"O Quarto ao Lado (2024)","url":"http://site.poupadefrutas.shop:80/movie/cleberson24/24danbury888BBB/1153267.mp4","active":true,"category":"Drama e História","type":"movie","isAdult":false,"logo":"https://image.tmdb.org/t/p/w600_and_h900_bestv2/xkR30rpo6Fl0jBZ6QKGR0GUARnK.jpg","tmdb":null},{"id":"m3u-1771698261477-1510","name":"Entre Amigas: De Volta ao Passado (2023)","url":"http://site.poupadefrutas.shop:80/movie/cleberson24/24danbury888BBB/1153272.mp4","active":true,"category":"Drama e História","type":"movie","isAdult":false,"logo":"https://image.tmdb.org/t/p/w600_and_h900_bestv2/kYcNLakH38pkA8SpwBtM6XFSAUA.jpg","tmdb":null},{"id":"m3u-1771698261477-5647","name":"A História de Fátima (2021)","url":"http://site.poupadefrutas.shop:80/movie/cleberson24/24danbury888BBB/1153280.mp4","active":true,"category":"Drama e História","type":"movie","isAdult":false,"logo":"https://image.tmdb.org/t/p/w600_and_h900_bestv2/bYh9DZsjHsfWnSYascGVaUznbu6.jpg","tmdb":null},{"id":"m3u-1771698261477-4579","name":"O Enxame (2023)","url":"http://site.poupadefrutas.shop:80/movie/cleberson24/24danbury888BBB/1153285.mp4","active":true,"category":"Drama e História","type":"movie","isAdult":false,"logo":"https://image.tmdb.org/t/p/w600_and_h900_bestv2/1mQzOwqCcTHiUHEsAZiHvlBPFo0.jpg","tmdb":null},{"id":"m3u-1771698261477-4293","name":"Macbeth - Vozes do Harlem (2021)","url":"http://site.poupadefrutas.shop:80/movie/cleberson24/24danbury888BBB/1153286.mp4","active":true,"category":"Drama e História","type":"movie","isAdult":false,"logo":"https://image.tmdb.org/t/p/w600_and_h900_bestv2/uzLXIUEDjGnskxTsKvxZtwzjYjT.jpg","tmdb":null},{"id":"m3u-1771698261477-8167","name":"A Barbárie (2023)","url":"http://site.poupadefrutas.shop:80/movie/cleberson24/24danbury888BBB/1153291.mp4","active":true,"category":"Drama e História","type":"movie","isAdult":false,"logo":"https://image.tmdb.org/t/p/w600_and_h900_bestv2/hIpVLbts9QKGkRJreMtVegq9akh.jpg","tmdb":null},{"id":"m3u-1771698261477-8763","name":"O Universo de Oliver (2022)","url":"http://site.poupadefrutas.shop:80/movie/cleberson24/24danbury888BBB/1153298.mp4","active":true,"category":"Drama e História","type":"movie","isAdult":false,"logo":"https://image.tmdb.org/t/p/w600_and_h900_bestv2/oiMmOzeRh5miENfdxGmpdT8ZMai.jpg","tmdb":null},{"id":"m3u-1771698261477-8416","name":"Eu Sou Charlie Walker (2022)","url":"http://site.poupadefrutas.shop:80/movie/cleberson24/24danbury888BBB/1153300.mp4","active":true,"category":"Drama e História","type":"movie","isAdult":false,"logo":"https://image.tmdb.org/t/p/w600_and_h900_bestv2/wpc91EcChyf0MqCh9Cx5O9T48og.jpg","tmdb":null},{"id":"m3u-1771698261477-756","name":"A Incrível História de Mario Capecchi (2022)","url":"http://site.poupadefrutas.shop:80/movie/cleberson24/24danbury888BBB/1153311.mp4","active":true,"category":"Drama e História","type":"movie","isAdult":false,"logo":"https://image.tmdb.org/t/p/w600_and_h900_bestv2/72wOmD7phuSYvun5NrYA8Js7VDk.jpg","tmdb":null},{"id":"m3u-1771698261477-5744","name":"Zelly e Eu (1988)","url":"http://site.poupadefrutas.shop:80/movie/cleberson24/24danbury888BBB/1203317.mp4","active":true,"category":"Drama e História","type":"movie","isAdult":false,"logo":"https://image.tmdb.org/t/p/w600_and_h900_bestv2/5OSvmtVS8UUZ6tz3bjceR54bGVa.jpg","tmdb":null},{"id":"m3u-1771698261477-5083","name":"Os Dois Hemisférios de Lucca (2025)","url":"http://site.poupadefrutas.shop:80/movie/cleberson24/24danbury888BBB/1203546.mp4","active":true,"category":"Drama e História","type":"movie","isAdult":false,"logo":"https://image.tmdb.org/t/p/w600_and_h900_bestv2/u226mX8Fr6eHpRnB0SBvZbWgSrJ.jpg","tmdb":null},{"id":"m3u-1771698261477-6851","name":"Ana: Uma adaptação da série Reis (2025)","url":"http://site.poupadefrutas.shop:80/movie/cleberson24/24danbury888BBB/1203564.mp4","active":true,"category":"Drama e História","type":"movie","isAdult":false,"logo":"https://image.tmdb.org/t/p/w600_and_h900_bestv2/jWlziUXDCb9KtmtKok7d2QsEdeO.jpg","tmdb":null},{"id":"m3u-1771698261477-3298","name":"Não Me Abandone (2025)","url":"http://site.poupadefrutas.shop:80/movie/cleberson24/24danbury888BBB/1203583.mp4","active":true,"category":"Drama e História","type":"movie","isAdult":false,"logo":"https://image.tmdb.org/t/p/w600_and_h900_bestv2/bAFX2cVPSurGach0Fq6DrBvQJ2V.jpg","tmdb":null},{"id":"m3u-1771698261477-6706","name":"Milagre do Destino (2025)","url":"http://site.poupadefrutas.shop:80/movie/cleberson24/24danbury888BBB/1203596.mp4","active":true,"category":"Drama e História","type":"movie","isAdult":false,"logo":"https://image.tmdb.org/t/p/w600_and_h900_bestv2/aacMhj1dcoHnAwuQpKWzGTxUSYw.jpg","tmdb":null},{"id":"m3u-1771698261477-9612","name":"Golpe de Superação (2025)","url":"http://site.poupadefrutas.shop:80/movie/cleberson24/24danbury888BBB/1203597.mp4","active":true,"category":"Drama e História","type":"movie","isAdult":false,"logo":"https://image.tmdb.org/t/p/w600_and_h900_bestv2/4ORO4zTiAI0lJedB3A05aWlFfmr.jpg","tmdb":null},{"id":"m3u-1771698261477-7151","name":"Desafie a Escuridão (2025)","url":"http://site.poupadefrutas.shop:80/movie/cleberson24/24danbury888BBB/1203598.mp4","active":true,"category":"Drama e História","type":"movie","isAdult":false,"logo":"https://image.tmdb.org/t/p/w600_and_h900_bestv2/eCHp6XoTo0t8dSKeVNQfTfR72Cp.jpg","tmdb":null},{"id":"m3u-1771698261477-2098","name":"Um Evento Crossover em Chicago (2025)","url":"http://site.poupadefrutas.shop:80/movie/cleberson24/24danbury888BBB/1203601.mp4","active":true,"category":"Drama e História","type":"movie","isAdult":false,"logo":"https://image.tmdb.org/t/p/w600_and_h900_bestv2/eAvakjAmP9eCktq5KppG6AUTzQ2.jpg","tmdb":null},{"id":"m3u-1771698261478-5656","name":"Inverno Sem Fim (2018)","url":"http://site.poupadefrutas.shop:80/movie/cleberson24/24danbury888BBB/1241364.mp4","active":true,"category":"Drama e História","type":"movie","isAdult":false,"logo":"https://image.tmdb.org/t/p/w600_and_h900_bestv2/riJ2M32mwrPBJb1STImzcij13bG.jpg","tmdb":null},{"id":"m3u-1771698261478-4152","name":"Os Emigrantes (2021)","url":"http://site.poupadefrutas.shop:80/movie/cleberson24/24danbury888BBB/1241864.mp4","active":true,"category":"Drama e História","type":"movie","isAdult":false,"logo":"https://image.tmdb.org/t/p/w600_and_h900_bestv2/59ihgrfeqiNgLPT9ltVpXQtAyxf.jpg","tmdb":null},{"id":"m3u-1771698261478-2966","name":"O Nosso Pai (2022)","url":"http://site.poupadefrutas.shop:80/movie/cleberson24/24danbury888BBB/1241887.mp4","active":true,"category":"Drama e História","type":"movie","isAdult":false,"logo":"https://image.tmdb.org/t/p/w600_and_h900_bestv2/jSGg3swiv9hNDpRxFwGu4P15zhq.jpg","tmdb":null},{"id":"m3u-1771698261489-9858","name":"Storm (2023)","url":"http://site.poupadefrutas.shop:80/movie/cleberson24/24danbury888BBB/1266959.mp4","active":true,"category":"Drama e História","type":"movie","isAdult":false,"logo":"https://image.tmdb.org/t/p/w600_and_h900_bestv2/kcUpT6kZQSkg3UDchzbpmeG8EYG.jpg","tmdb":null}]